mcp_remote_macos_use/__init__.py
mcp_remote_macos_use/livekit_handler.py
mcp_remote_macos_use/server.py
mseep_mcp_remote_macos_use-0.1.2.dist-info/METADATA
mseep_mcp_remote_macos_use-0.1.2.dist-info/WHEEL
mseep_mcp_remote_macos_use-0.1.2.dist-info/entry_points.txt
mseep_mcp_remote_macos_use-0.1.2.dist-info/licenses/LICENSE
mseep_mcp_remote_macos_use-0.1.2.dist-info/RECORD
