Metadata-Version: 2.4
Name: mseep-mcp_remote_macos_use
Version: 0.1.2
Summary: A MCP server for remote MacOS control
Author-email: mseep <support@skydeck.ai>
Maintainer-email: mseep <support@skydeck.ai>
License-File: LICENSE
Requires-Python: >=3.10
Requires-Dist: aiohttp>=3.8.1
Requires-Dist: aiortc>=1.3.2
Requires-Dist: anthropic>=0.49.0
Requires-Dist: cryptography>=44.0.0
Requires-Dist: livekit-api>=1.0.2
Requires-Dist: livekit>=1.0.5
Requires-Dist: mcp>=1.4.1
Requires-Dist: paramiko>=3.5.1
Requires-Dist: pillow>=10.0.0
Requires-Dist: pydes>=2.0.1
Requires-Dist: python-dotenv>=1.0.1
Requires-Dist: websockets>=10.0
